<?xml version="1.0" encoding="UTF-8"?>
<catalog xmlns="http://www.unidata.ucar.edu/namespaces/thredds/InvCatalog/v1.0"
  xmlns:xlink="http://www.w3.org/1999/xlink"
  name="THREDDS Top Catalog, points to other THREDDS catalogs" version="1.0.1">
  <dataset name="USGS Woods Hole Science Center THREDDS catalogs">
    <catalogRef xlink:href="spill_models.xml"      xlink:title="Circulation models containing Gulf of Mexico" name=""/>
    <catalogRef xlink:href="adria_catalog.xml"      xlink:title="Adriatic Sea Project" name=""/>
    <catalogRef xlink:href="bathy_catalog.xml"      xlink:title="Bathymetry" name=""/>
    <catalogRef xlink:href="carolinas_catalog.xml"      xlink:title="Carolina Coastal Change Project" name=""/>
    <catalogRef xlink:href="gom_interop_catalog.xml"      xlink:title="Gulf of Maine Interoperability Demo" name=""/>
         <catalogRef xlink:href="ioos_catalog_top.xml"      xlink:title="IOOS Top Level THREDDS Data Server Catalogs" name=""/>
    <catalogRef xlink:href="ioos_clean.xml"      xlink:title="IOOS Clean Catalog (only aggregated, CF-compliant data)" name=""/>
    <catalogRef xlink:href="mass_bay_catalog.xml"      xlink:title="Massachusetts Bay Project" name=""/>
      <catalogRef xlink:href="roms_catalog.xml"      xlink:title="ROMS Forecast Models Catalog" name=""/>
       <catalogRef xlink:href="vineyard_sound_catalog.xml"      xlink:title="Vineyard Sound/Middle Ground Project" name=""/>
    <catalogRef xlink:href="wake_catalog.xml"      xlink:title="Island Wake Simulations" name=""/>
    <catalogRef xlink:href="mvco_catalog.xml"      xlink:title="MVCO ROMS-SWAN Model Runs" name=""/>
    <catalogRef xlink:href="latte_catalog.xml"      xlink:title="Latte Runs" name=""/>
    <catalogRef xlink:href="pv_catalog.xml"      xlink:title="PV 2002 Runs" name=""/>
    <catalogRef xlink:href="allts_catalog.xml"      xlink:title="CMGP Oceanographic Time Series Data" name=""/>  
    <catalogRef xlink:href="buzzards_catalog.xml"      xlink:title="Buzzards Bay Runs" name=""/>
  </dataset>
</catalog>
